kutil/__init__.py
kutil/format.py
kutil/iterator_help.py
kutil/math_help.py
kutil/progress.py
kutil/runtime.py
kutil/typing_help.py
kutil/buffer/AppendedByteBuffer.py
kutil/buffer/BidirectionalByteArray.py
kutil/buffer/ByteBuffer.py
kutil/buffer/DataBuffer.py
kutil/buffer/FileByteBuffer.py
kutil/buffer/MemoryByteBuffer.py
kutil/buffer/Serializable.py
kutil/buffer/TextOutput.py
kutil/buffer/__init__.py
kutil/io/__init__.py
kutil/io/directory.py
kutil/io/file.py
kutil/io/native_io_wrapper.py
kutil/language/AST.py
kutil/language/BytecodeFile.py
kutil/language/Compiler.py
kutil/language/Error.py
kutil/language/Interpreter.py
kutil/language/Language.py
kutil/language/Lexer.py
kutil/language/Options.py
kutil/language/Parser.py
kutil/language/Stack.py
kutil/language/Token.py
kutil/language/__init__.py
kutil/language/languages/BrainFuck.py
kutil/language/languages/__init__.py
kutil/language/languages/javascript/JSLexer.py
kutil/language/languages/javascript/JSOptions.py
kutil/language/languages/javascript/JSParser.py
kutil/language/languages/javascript/Javascript.py
kutil/language/languages/javascript/__init__.py
kutil/language/languages/javascript/character.py
kutil/language/languages/javascript/error_handler.py
kutil/language/languages/javascript/messages.py
kutil/language/languages/javascript/nodes.py
kutil/language/languages/javascript/syntax.py
kutil/language/languages/paint_tryhard/Canvas.py
kutil/language/languages/paint_tryhard/Employee.py
kutil/language/languages/paint_tryhard/PTCompiler.py
kutil/language/languages/paint_tryhard/PTInterpreter.py
kutil/language/languages/paint_tryhard/PTLexer.py
kutil/language/languages/paint_tryhard/PTParser.py
kutil/language/languages/paint_tryhard/PaintTryhard.py
kutil/language/languages/paint_tryhard/__init__.py
kutil/language/languages/paint_tryhard/jobs/__init__.py
kutil/language/languages/paint_tryhard/jobs/boss.py
kutil/language/languages/paint_tryhard/jobs/mathematician.py
kutil_jakubaugustyn-0.1.6.dist-info/licenses/LICENSE
kutil_jakubaugustyn-0.1.6.dist-info/METADATA
kutil_jakubaugustyn-0.1.6.dist-info/WHEEL
kutil_jakubaugustyn-0.1.6.dist-info/top_level.txt
kutil_jakubaugustyn-0.1.6.dist-info/RECORD
