Metadata-Version: 2.4
Name: KUtil-jakubaugustyn
Version: 0.1.6
Summary: Kuba's Python Utilities
Author-email: Jakub Augustýn <kubik.augustyn@post.cz>, Radek Augustýn <raugustyn@post.cz>
Project-URL: Homepage, https://github.com/kubikaugustyn/KUtil
Project-URL: Issues, https://github.com/kubikaugustyn/KUtil/issues
Classifier: Programming Language :: Python :: 3
Classifier: Operating System :: OS Independent
Requires-Python: >=3.12
License-File: LICENSE
Requires-Dist: cryptography>=46.0.3
Requires-Dist: certifi>=2025.10.5
Requires-Dist: requests==2.*
Requires-Dist: urllib3==2.*
Requires-Dist: typeguard==4.*
Requires-Dist: deprecation==2.*
Requires-Dist: frozenlist
Requires-Dist: colorama
Dynamic: license-file
